SVN_checkout/fetch_Lib_SVN.py
SVN_checkout-0.0.7.dist-info/LICENSE.txt
SVN_checkout-0.0.7.dist-info/METADATA
SVN_checkout-0.0.7.dist-info/WHEEL
SVN_checkout-0.0.7.dist-info/top_level.txt
SVN_checkout-0.0.7.dist-info/RECORD
